{
  "formatVersion": 1,
  "database": {
    "version": 1,
    "identityHash": "3024f50a46c7b411945733ca75efb0f2",
    "entities": [
      {
        "tableName": "documents",
        "createSql": "CREATE TABLE IF NOT EXISTS `${TABLE_NAME}` (`id` INTEGER PRIMARY KEY AUTOINCREMENT NOT NULL, `name` TEXT NOT NULL, `file_path` TEXT NOT NULL, `created_at` INTEGER NOT NULL, `last_modified_at` INTEGER NOT NULL)",
        "fields": [
          {
            "fieldPath": "id",
            "columnName": "id",
            "affinity": "INTEGER",
            "notNull": true
          },
          {
            "fieldPath": "name",
            "columnName": "name",
            "affinity": "TEXT",
            "notNull": true
          },
          {
            "fieldPath": "filePath",
            "columnName": "file_path",
            "affinity": "TEXT",
            "notNull": true
          },
          {
            "fieldPath": "createdAt",
            "columnName": "created_at",
            "affinity": "INTEGER",
            "notNull": true
          },
          {
            "fieldPath": "lastModifiedAt",
            "columnName": "last_modified_at",
            "affinity": "INTEGER",
            "notNull": true
          }
        ],
        "primaryKey": {
          "autoGenerate": true,
          "columnNames": [
            "id"
          ]
        },
        "indices": [
          {
            "name": "index_documents_file_path",
            "unique": false,
            "columnNames": [
              "file_path"
            ],
            "orders": [],
            "createSql": "CREATE INDEX IF NOT EXISTS `index_documents_file_path` ON `${TABLE_NAME}` (`file_path`)"
          }
        ],
        "foreignKeys": []
      },
      {
        "tableName": "version_snapshots",
        "createSql": "CREATE TABLE IF NOT EXISTS `${TABLE_NAME}` (`id` INTEGER PRIMARY KEY AUTOINCREMENT NOT NULL, `document_id` INTEGER NOT NULL, `version_number` INTEGER NOT NULL, `timestamp` INTEGER NOT NULL, `patch_data` TEXT NOT NULL, `description` TEXT, FOREIGN KEY(`document_id`) REFERENCES `documents`(`id`) ON UPDATE NO ACTION ON DELETE CASCADE )",
        "fields": [
          {
            "fieldPath": "id",
            "columnName": "id",
            "affinity": "INTEGER",
            "notNull": true
          },
          {
            "fieldPath": "documentId",
            "columnName": "document_id",
            "affinity": "INTEGER",
            "notNull": true
          },
          {
            "fieldPath": "versionNumber",
            "columnName": "version_number",
            "affinity": "INTEGER",
            "notNull": true
          },
          {
            "fieldPath": "timestamp",
            "columnName": "timestamp",
            "affinity": "INTEGER",
            "notNull": true
          },
          {
            "fieldPath": "patchData",
            "columnName": "patch_data",
            "affinity": "TEXT",
            "notNull": true
          },
          {
            "fieldPath": "description",
            "columnName": "description",
            "affinity": "TEXT",
            "notNull": false
          }
        ],
        "primaryKey": {
          "autoGenerate": true,
          "columnNames": [
            "id"
          ]
        },
        "indices": [
          {
            "name": "index_version_snapshots_document_id_version_number",
            "unique": true,
            "columnNames": [
              "document_id",
              "version_number"
            ],
            "orders": [],
            "createSql": "CREATE UNIQUE INDEX IF NOT EXISTS `index_version_snapshots_document_id_version_number` ON `${TABLE_NAME}` (`document_id`, `version_number`)"
          }
        ],
        "foreignKeys": [
          {
            "table": "documents",
            "onDelete": "CASCADE",
            "onUpdate": "NO ACTION",
            "columns": [
              "document_id"
            ],
            "referencedColumns": [
              "id"
            ]
          }
        ]
      }
    ],
    "views": [],
    "setupQueries": [
      "CREATE TABLE IF NOT EXISTS room_master_table (id INTEGER PRIMARY KEY,identity_hash TEXT)",
      "INSERT OR REPLACE INTO room_master_table (id,identity_hash) VALUES(42, '3024f50a46c7b411945733ca75efb0f2')"
    ]
  }
}